html_from_epub/__init__.py
html_from_epub/html_from_epub.py
html_from_epub-0.2.1.data/scripts/html-from-epub
html_from_epub-0.2.1.dist-info/LICENSE
html_from_epub-0.2.1.dist-info/METADATA
html_from_epub-0.2.1.dist-info/WHEEL
html_from_epub-0.2.1.dist-info/top_level.txt
html_from_epub-0.2.1.dist-info/RECORD
