Metadata-Version: 2.1
Name: html-from-epub
Version: 0.2.1
Summary: Extract html library from Epub file
Home-page: https://github.com/casperlehmann/html-from-epub
Author: Casper Lehmann
Author-email: casperlehmann@gmail.com
License: UNKNOWN
Platform: UNKNOWN
Classifier: Programming Language :: Python :: 3
Classifier: License :: OSI Approved :: MIT License
Classifier: Operating System :: OS Independent
Requires-Python: >=3.6
Requires-Dist: EbookLib
